<item><country>Italy</country><league>Serie A</league><season>2015/2016</season><stage>10</stage><matchId>2060448</matchId><date>2015-10-29 15:45</date><homeTeamId><value>8564</value></homeTeamId><awayTeamId><value>8533</value></awayTeamId><homeTeamFullName><value>AC Milan</value></homeTeamFullName><awayTeamFullName><value>Chievo</value></awayTeamFullName><homeTeamAcronym><value>ACM</value></homeTeamAcronym><awayTeamAcronym><value>CHI</value></awayTeamAcronym><homeTeamGoal>None</homeTeamGoal><awayTeamGoal>None</awayTeamGoal><homePlayers><value>Gianluigi Donnarumma</value><value>Ignazio Abate</value><value>Alex</value><value>Alessio Romagnoli</value><value>Luca Antonelli</value><value>Juraj Kucka</value><value>Riccardo Montolivo</value><value>Andrea Bertolacci</value><value>Alessio Cerci</value><value>Carlos Bacca</value><value>Giacomo Bonaventura</value></homePlayers><awayPlayers><value>Albano Benjamin Bizzarri</value><value>Nicholas Sebastian Frey</value><value>Bostjan Cesar</value><value>Dario Dainelli</value><value>Massimo Gobbi</value><value>Giampiero Pinzi</value><value>Ivan Radovanovic</value><value>Lucas Nahuel Castro</value><value>Valter Birsa</value><value>Sergio Pellissier</value><value>Alberto Paloschi</value></awayPlayers><homePlayersId><value>618878</value><value>362195</value><value>39555</value><value>46374</value><value>26564</value><value>24507</value><value>72518</value><value>154239</value><value>41269</value><value>127460</value><value>166648</value></homePlayersId><awayPlayersId><value>37503</value><value>39304</value><value>26223</value><value>33816</value><value>42008</value><value>27731</value><value>15732</value><value>166509</value><value>36121</value><value>24448</value><value>109121</value></awayPlayersId><homePlayersX><value>1</value><value>2</value><value>4</value><value>6</value><value>8</value><value>3</value><value>5</value><value>7</value><value>3</value><value>5</value><value>7</value></homePlayersX><awayPlayersX><value>1</value><value>2</value><value>4</value><value>6</value><value>8</value><value>3</value><value>5</value><value>7</value><value>5</value><value>4</value><value>6</value></awayPlayersX><homePlayersY><value>1</value><value>3</value><value>3</value><value>3</value><value>3</value><value>7</value><value>7</value><value>7</value><value>10</value><value>10</value><value>10</value></homePlayersY><awayPlayersY><value>1</value><value>3</value><value>3</value><value>3</value><value>3</value><value>6</value><value>6</value><value>6</value><value>8</value><value>10</value><value>10</value></awayPlayersY><goal><value><event_incident_typefk>393</event_incident_typefk><elapsed>53</elapsed><comment>n</comment><sortorder>1</sortorder><type>goal</type><subtype>shot</subtype><goal_type>n</goal_type><coordinates><value>14</value><value>8</value></coordinates><team>8564</team><player1>46374</player1><player2>166648</player2><stats><goals>1</goals><shoton>1</shoton></stats><id>4964835</id><n>367</n></value></goal><shoton><value><event_incident_typefk>136</event_incident_typefk><elapsed>3</elapsed><sortorder>1</sortorder><type>shoton</type><subtype>header</subtype><coordinates><value>25</value><value>63</value></coordinates><team>8533</team><player1>166509</player1><stats><shoton>1</shoton></stats><id>4963723</id><n>47</n></value><value><event_incident_typefk>312</event_incident_typefk><elapsed>4</elapsed><sortorder>0</sortorder><type>shoton</type><subtype>deflected</subtype><coordinates><value>23</value><value>16</value></coordinates><team>8564</team><player1>72518</player1><stats><shoton>1</shoton></stats><id>4963737</id><n>53</n></value><value><event_incident_typefk>68</event_incident_typefk><elapsed>17</elapsed><sortorder>2</sortorder><type>shoton</type><subtype>shot</subtype><coordinates><value>12</value><value>54</value></coordinates><team>8533</team><player1>27731</player1><stats><shoton>1</shoton></stats><id>4964002</id><n>145</n></value><value><event_incident_typefk>61</event_incident_typefk><elapsed>25</elapsed><sortorder>0</sortorder><type>shoton</type><subtype>blocked_shot</subtype><coordinates><value>30</value><value>6</value></coordinates><team>8564</team><player1>166648</player1><stats><blocked>1</blocked></stats><id>4964156</id><n>188</n></value><value><event_incident_typefk>61</event_incident_typefk><elapsed>39</elapsed><sortorder>2</sortorder><type>shoton</type><subtype>blocked_shot</subtype><coordinates><value>29</value><value>13</value></coordinates><team>8564</team><player1>154239</player1><stats><blocked>1</blocked></stats><id>4964463</id><n>250</n></value><value><event_incident_typefk>148</event_incident_typefk><elapsed>44</elapsed><sortorder>1</sortorder><type>shoton</type><subtype>header</subtype><coordinates><value>24</value><value>64</value></coordinates><team>8533</team><player1>24448</player1><stats><shoton>1</shoton></stats><id>4964573</id><n>283</n></value><value><event_incident_typefk>135</event_incident_typefk><elapsed>46</elapsed><sortorder>3</sortorder><type>shoton</type><subtype>shot</subtype><coordinates><value>31</value><value>15</value></coordinates><team>8564</team><player1>288613</player1><stats><shoton>1</shoton></stats><id>4964730</id><n>325</n></value><value><event_incident_typefk>142</event_incident_typefk><elapsed>51</elapsed><sortorder>1</sortorder><type>shoton</type><subtype>header</subtype><coordinates><value>25</value><value>6</value></coordinates><team>8564</team><player1>72518</player1><stats><shoton>1</shoton></stats><id>4964803</id><n>349</n></value><value><event_incident_typefk>135</event_incident_typefk><elapsed>60</elapsed><sortorder>0</sortorder><type>shoton</type><subtype>shot</subtype><coordinates><value>27</value><value>15</value></coordinates><team>8564</team><player1>127460</player1><stats><shoton>1</shoton></stats><id>4964990</id><n>415</n></value><value><event_incident_typefk>552</event_incident_typefk><elapsed>68</elapsed><sortorder>0</sortorder><type>shoton</type><subtype>big chance shot</subtype><coordinates><value>15</value><value>65</value></coordinates><team>8533</team><player1>109121</player1><stats><shoton>1</shoton></stats><id>4965136</id><n>451</n></value><value><event_incident_typefk>61</event_incident_typefk><elapsed>80</elapsed><sortorder>1</sortorder><type>shoton</type><subtype>blocked_shot</subtype><coordinates><value>32</value><value>10</value></coordinates><team>8564</team><player1>166648</player1><stats><blocked>1</blocked></stats><id>4965337</id><n>486</n></value></shoton><shotoff><value><event_incident_typefk>47</event_incident_typefk><elapsed>22</elapsed><sortorder>1</sortorder><type>shotoff</type><subtype>header</subtype><coordinates><value>26</value><value>8</value></coordinates><team>8564</team><player1>154239</player1><stats><shotoff>1</shotoff></stats><id>4964098</id><n>168</n></value><value><event_incident_typefk>46</event_incident_typefk><elapsed>29</elapsed><sortorder>0</sortorder><type>shotoff</type><subtype>shot</subtype><coordinates><value>28</value><value>16</value></coordinates><team>8564</team><player1>127460</player1><stats><shotoff>1</shotoff></stats><id>4964239</id><n>200</n></value><value><event_incident_typefk>46</event_incident_typefk><elapsed>34</elapsed><sortorder>0</sortorder><type>shotoff</type><subtype>shot</subtype><coordinates><value>33</value><value>8</value></coordinates><team>8564</team><player1>41269</player1><stats><shotoff>1</shotoff></stats><id>4964345</id><n>220</n></value><value><event_incident_typefk>46</event_incident_typefk><elapsed>41</elapsed><sortorder>0</sortorder><type>shotoff</type><subtype>shot</subtype><coordinates><value>31</value><value>56</value></coordinates><team>8533</team><player1>166509</player1><stats><shotoff>1</shotoff></stats><id>4964500</id><n>264</n></value><value><event_incident_typefk>47</event_incident_typefk><elapsed>42</elapsed><sortorder>2</sortorder><type>shotoff</type><subtype>header</subtype><coordinates><value>26</value><value>6</value></coordinates><team>8564</team><player1>41269</player1><stats><shotoff>1</shotoff></stats><id>4964533</id><n>272</n></value><value><event_incident_typefk>53</event_incident_typefk><elapsed>45</elapsed><elapsed_plus>2</elapsed_plus><sortorder>13</sortorder><type>shotoff</type><subtype>volley</subtype><coordinates><value>33</value><value>11</value></coordinates><team>8564</team><player1>127460</player1><stats><shotoff>1</shotoff></stats><id>4964633</id><n>314</n></value><value><event_incident_typefk>317</event_incident_typefk><elapsed>63</elapsed><sortorder>1</sortorder><type>shotoff</type><subtype>deflected</subtype><coordinates><value>29</value><value>12</value></coordinates><team>8564</team><player1>72518</player1><stats><shotoff>1</shotoff></stats><id>4965048</id><n>436</n></value><value><event_incident_typefk>46</event_incident_typefk><elapsed>66</elapsed><sortorder>1</sortorder><type>shotoff</type><subtype>shot</subtype><coordinates><value>27</value><value>15</value></coordinates><team>8564</team><player1>72518</player1><stats><shotoff>1</shotoff></stats><id>4965116</id><n>443</n></value><value><event_incident_typefk>9</event_incident_typefk><elapsed>72</elapsed><sortorder>1</sortorder><type>shotoff</type><subtype>distance</subtype><coordinates><value>37</value><value>15</value></coordinates><team>8564</team><player1>288613</player1><stats><shotoff>1</shotoff></stats><id>4965222</id><n>472</n></value><value><event_incident_typefk>46</event_incident_typefk><elapsed>77</elapsed><sortorder>0</sortorder><type>shotoff</type><subtype>shot</subtype><coordinates><value>20</value><value>10</value></coordinates><team>8564</team><player1>127460</player1><stats><shotoff>1</shotoff></stats><id>4965303</id><n>480</n></value><value><event_incident_typefk>624</event_incident_typefk><elapsed>81</elapsed><sortorder>0</sortorder><type>shotoff</type><subtype>bad shot</subtype><coordinates><value>17</value><value>9</value></coordinates><team>8564</team><player1>166648</player1><stats><shotoff>1</shotoff></stats><id>4965349</id><n>495</n></value><value><event_incident_typefk>46</event_incident_typefk><elapsed>82</elapsed><sortorder>2</sortorder><type>shotoff</type><subtype>shot</subtype><coordinates><value>17</value><value>11</value></coordinates><team>8564</team><player1>72518</player1><stats><shotoff>1</shotoff></stats><id>4965376</id><n>501</n></value><value><event_incident_typefk>46</event_incident_typefk><elapsed>88</elapsed><sortorder>1</sortorder><type>shotoff</type><subtype>shot</subtype><coordinates><value>27</value><value>17</value></coordinates><team>8564</team><player1>72518</player1><stats><shotoff>1</shotoff></stats><id>4965499</id><n>521</n></value><value><event_incident_typefk>47</event_incident_typefk><elapsed>89</elapsed><sortorder>2</sortorder><type>shotoff</type><subtype>header</subtype><coordinates><value>26</value><value>3</value></coordinates><team>8564</team><player1>72518</player1><stats><shotoff>1</shotoff></stats><id>4965524</id><n>525</n></value><value><event_incident_typefk>46</event_incident_typefk><elapsed>90</elapsed><elapsed_plus>3</elapsed_plus><sortorder>7</sortorder><type>shotoff</type><subtype>shot</subtype><coordinates><value>32</value><value>10</value></coordinates><team>8564</team><player1>47041</player1><stats><shotoff>1</shotoff></stats><id>4965571</id><n>544</n></value></shotoff><card><value><event_incident_typefk>70</event_incident_typefk><elapsed>50</elapsed><comment>y</comment><sortorder>1</sortorder><type>card</type><card_type>y</card_type><team>8533</team><player1>27731</player1><stats><ycards>1</ycards></stats><id>4964865</id><n>371</n></value><value><event_incident_typefk>505</event_incident_typefk><elapsed>58</elapsed><comment>y</comment><sortorder>1</sortorder><type>card</type><subtype>Unsportsmanlike Cond</subtype><card_type>y</card_type><team>8533</team><player1>26223</player1><stats><ycards>1</ycards></stats><id>4964953</id><n>408</n></value></card><cross><value><event_incident_typefk>774</event_incident_typefk><elapsed>3</elapsed><sortorder>0</sortorder><type>cross</type><subtype>cross</subtype><coordinates><value>35</value><value>49</value></coordinates><team>8533</team><player1>36121</player1><stats><crosses>1</crosses></stats><id>4963721</id><n>44</n></value><value><event_incident_typefk>7</event_incident_typefk><elapsed>5</elapsed><sortorder>0</sortorder><type>cross</type><subtype>cross</subtype><coordinates><value>41</value><value>9</value></coordinates><team>8564</team><player1>41269</player1><stats><crosses>1</crosses></stats><id>4963758</id><n>64</n></value><value><event_incident_typefk>774</event_incident_typefk><elapsed>15</elapsed><sortorder>1</sortorder><type>cross</type><subtype>cross</subtype><coordinates><value>38</value><value>20</value></coordinates><team>8564</team><player1>127460</player1><stats><crosses>1</crosses></stats><id>4963969</id><n>126</n></value><value><event_incident_typefk>770</event_incident_typefk><elapsed>16</elapsed><sortorder>1</sortorder><type>cross</type><subtype>cross</subtype><coordinates><value>29</value><value>48</value></coordinates><team>8533</team><player1>15732</player1><stats><crosses>1</crosses></stats><id>4963986</id><n>133</n></value><value><event_incident_typefk>770</event_incident_typefk><elapsed>16</elapsed><sortorder>3</sortorder><type>cross</type><subtype>cross</subtype><coordinates><value>41</value><value>54</value></coordinates><team>8533</team><player1>36121</player1><stats><crosses>1</crosses></stats><id>4963991</id><n>141</n></value><value><event_incident_typefk>7</event_incident_typefk><elapsed>22</elapsed><sortorder>0</sortorder><type>cross</type><subtype>cross</subtype><coordinates><value>42</value><value>12</value></coordinates><team>8564</team><player1>41269</player1><stats><crosses>1</crosses></stats><id>4964095</id><n>164</n></value><value><event_incident_typefk>7</event_incident_typefk><elapsed>35</elapsed><sortorder>0</sortorder><type>cross</type><subtype>cross</subtype><coordinates><value>14</value><value>50</value></coordinates><team>8533</team><player1>166509</player1><stats><crosses>1</crosses></stats><id>4964384</id><n>223</n></value><value><event_incident_typefk>7</event_incident_typefk><elapsed>36</elapsed><sortorder>1</sortorder><type>cross</type><subtype>cross</subtype><coordinates><value>42</value><value>14</value></coordinates><team>8564</team><player1>288613</player1><stats><crosses>1</crosses></stats><id>4964398</id><n>234</n></value><value><event_incident_typefk>770</event_incident_typefk><elapsed>38</elapsed><sortorder>0</sortorder><type>cross</type><subtype>cross</subtype><coordinates><value>41</value><value>3</value></coordinates><team>8564</team><player1>288613</player1><stats><crosses>1</crosses></stats><id>4964445</id><n>241</n></value><value><event_incident_typefk>7</event_incident_typefk><elapsed>39</elapsed><sortorder>0</sortorder><type>cross</type><subtype>cross</subtype><coordinates><value>5</value><value>13</value></coordinates><team>8564</team><player1>72518</player1><stats><crosses>1</crosses></stats><id>4964459</id><n>242</n></value><value><event_incident_typefk>7</event_incident_typefk><elapsed>39</elapsed><sortorder>3</sortorder><type>cross</type><subtype>cross</subtype><coordinates><value>37</value><value>14</value></coordinates><team>8564</team><player1>127460</player1><stats><crosses>1</crosses></stats><id>4964467</id><n>251</n></value><value><event_incident_typefk>7</event_incident_typefk><elapsed>42</elapsed><sortorder>1</sortorder><type>cross</type><subtype>cross</subtype><coordinates><value>42</value><value>15</value></coordinates><team>8564</team><player1>288613</player1><stats><crosses>1</crosses></stats><id>4964532</id><n>267</n></value><value><event_incident_typefk>774</event_incident_typefk><elapsed>44</elapsed><sortorder>0</sortorder><type>cross</type><subtype>cross</subtype><coordinates><value>33</value><value>46</value></coordinates><team>8533</team><player1>36121</player1><stats><crosses>1</crosses></stats><id>4964569</id><n>275</n></value><value><event_incident_typefk>7</event_incident_typefk><elapsed>45</elapsed><sortorder>0</sortorder><type>cross</type><subtype>cross</subtype><coordinates><value>3</value><value>64</value></coordinates><team>8533</team><player1>36121</player1><stats><crosses>1</crosses></stats><id>4964582</id><n>291</n></value><value><event_incident_typefk>770</event_incident_typefk><elapsed>45</elapsed><elapsed_plus>1</elapsed_plus><sortorder>6</sortorder><type>cross</type><subtype>cross</subtype><coordinates><value>39</value><value>4</value></coordinates><team>8564</team><player1>166648</player1><stats><crosses>1</crosses></stats><id>4964609</id><n>302</n></value><value><event_incident_typefk>770</event_incident_typefk><elapsed>45</elapsed><elapsed_plus>2</elapsed_plus><sortorder>11</sortorder><type>cross</type><subtype>cross</subtype><coordinates><value>11</value><value>15</value></coordinates><team>8564</team><player1>24507</player1><stats><crosses>1</crosses></stats><id>4964630</id><n>310</n></value><value><event_incident_typefk>774</event_incident_typefk><elapsed>51</elapsed><sortorder>0</sortorder><type>cross</type><subtype>cross</subtype><coordinates><value>10</value><value>14</value></coordinates><team>8564</team><player1>127460</player1><stats><crosses>1</crosses></stats><id>4964801</id><n>332</n></value><value><event_incident_typefk>7</event_incident_typefk><elapsed>51</elapsed><sortorder>2</sortorder><type>cross</type><subtype>cross</subtype><coordinates><value>13</value><value>6</value></coordinates><team>8564</team><player1>72518</player1><stats><crosses>1</crosses></stats><id>4964804</id><n>335</n></value><value><event_incident_typefk>7</event_incident_typefk><elapsed>51</elapsed><sortorder>4</sortorder><type>cross</type><subtype>cross</subtype><coordinates><value>40</value><value>16</value></coordinates><team>8564</team><player1>288613</player1><stats><crosses>1</crosses></stats><id>4964807</id><n>347</n></value><value><event_incident_typefk>7</event_incident_typefk><elapsed>52</elapsed><sortorder>2</sortorder><type>cross</type><subtype>cross</subtype><coordinates><value>37</value><value>2</value></coordinates><team>8564</team><player1>154239</player1><stats><crosses>1</crosses></stats><id>4964830</id><n>355</n></value><value><event_incident_typefk>774</event_incident_typefk><elapsed>55</elapsed><sortorder>0</sortorder><type>cross</type><subtype>cross</subtype><coordinates><value>8</value><value>54</value></coordinates><team>8533</team><player1>36121</player1><stats><crosses>1</crosses></stats><id>4964878</id><n>374</n></value><value><event_incident_typefk>7</event_incident_typefk><elapsed>59</elapsed><sortorder>0</sortorder><type>cross</type><subtype>cross</subtype><coordinates><value>10</value><value>56</value></coordinates><team>8533</team><player1>27731</player1><stats><crosses>1</crosses></stats><id>4964968</id><n>410</n></value><value><event_incident_typefk>7</event_incident_typefk><elapsed>61</elapsed><sortorder>0</sortorder><type>cross</type><subtype>cross</subtype><coordinates><value>41</value><value>57</value></coordinates><team>8533</team><player1>33816</player1><stats><crosses>1</crosses></stats><id>4965008</id><n>421</n></value><value><event_incident_typefk>7</event_incident_typefk><elapsed>61</elapsed><sortorder>2</sortorder><type>cross</type><subtype>cross</subtype><coordinates><value>41</value><value>52</value></coordinates><team>8533</team><player1>24448</player1><stats><crosses>1</crosses></stats><id>4965014</id><n>422</n></value><value><event_incident_typefk>7</event_incident_typefk><elapsed>63</elapsed><sortorder>3</sortorder><type>cross</type><subtype>cross</subtype><coordinates><value>4</value><value>5</value></coordinates><team>8564</team><player1>41269</player1><stats><crosses>1</crosses></stats><id>4965053</id><n>431</n></value><value><event_incident_typefk>7</event_incident_typefk><elapsed>68</elapsed><sortorder>3</sortorder><type>cross</type><subtype>cross</subtype><coordinates><value>42</value><value>57</value></coordinates><team>8533</team><player1>33816</player1><stats><crosses>1</crosses></stats><id>4965145</id><n>458</n></value><value><event_incident_typefk>7</event_incident_typefk><elapsed>71</elapsed><sortorder>1</sortorder><type>cross</type><subtype>cross</subtype><coordinates><value>9</value><value>7</value></coordinates><team>8564</team><player1>127460</player1><stats><crosses>1</crosses></stats><id>4965212</id><n>469</n></value><value><event_incident_typefk>7</event_incident_typefk><elapsed>82</elapsed><sortorder>0</sortorder><type>cross</type><subtype>cross</subtype><coordinates><value>3</value><value>12</value></coordinates><team>8564</team><player1>46374</player1><stats><crosses>1</crosses></stats><id>4965372</id><n>500</n></value><value><event_incident_typefk>7</event_incident_typefk><elapsed>87</elapsed><sortorder>0</sortorder><type>cross</type><subtype>cross</subtype><coordinates><value>5</value><value>63</value></coordinates><team>8533</team><player1>109121</player1><stats><crosses>1</crosses></stats><id>4965481</id><n>517</n></value><value><event_incident_typefk>123</event_incident_typefk><elapsed>90</elapsed><elapsed_plus>3</elapsed_plus><sortorder>10</sortorder><type>throwin</type><subtype>cross</subtype><team>8533</team><id>4965579</id><n>550</n></value><value><event_incident_typefk>7</event_incident_typefk><elapsed>90</elapsed><elapsed_plus>3</elapsed_plus><sortorder>12</sortorder><type>cross</type><subtype>cross</subtype><coordinates><value>16</value><value>53</value></coordinates><team>8533</team><player1>15732</player1><stats><crosses>1</crosses></stats><id>4965583</id><n>560</n></value></cross><corner><value><event_incident_typefk>867</event_incident_typefk><elapsed>17</elapsed><sortorder>0</sortorder><type>corner</type><subtype>cross_left</subtype><coordinates><value>45</value><value>69</value></coordinates><team>8533</team><player1>36121</player1><stats><corners>1</corners></stats><id>4963999</id><n>143</n></value><value><event_incident_typefk>873</event_incident_typefk><elapsed>25</elapsed><sortorder>1</sortorder><type>corner</type><subtype>short_right</subtype><coordinates><value>45</value><value>1</value></coordinates><team>8564</team><player1>41269</player1><stats><corners>1</corners></stats><id>4964164</id><n>189</n></value><value><event_incident_typefk>871</event_incident_typefk><elapsed>44</elapsed><sortorder>2</sortorder><type>corner</type><subtype>short_left</subtype><coordinates><value>45</value><value>69</value></coordinates><team>8533</team><player1>15732</player1><stats><corners>1</corners></stats><id>4964580</id><n>287</n></value><value><event_incident_typefk>867</event_incident_typefk><elapsed>45</elapsed><elapsed_plus>1</elapsed_plus><sortorder>4</sortorder><type>corner</type><subtype>cross_left</subtype><coordinates><value>1</value><value>1</value></coordinates><team>8564</team><player1>127460</player1><stats><corners>1</corners></stats><id>4964603</id><n>301</n></value><value><event_incident_typefk>873</event_incident_typefk><elapsed>45</elapsed><elapsed_plus>1</elapsed_plus><sortorder>7</sortorder><type>corner</type><subtype>short_right</subtype><coordinates><value>45</value><value>1</value></coordinates><team>8564</team><player1>166648</player1><stats><corners>1</corners></stats><id>4964612</id><n>303</n></value><value><event_incident_typefk>869</event_incident_typefk><elapsed>45</elapsed><elapsed_plus>2</elapsed_plus><sortorder>9</sortorder><type>corner</type><subtype>cross_right</subtype><coordinates><value>45</value><value>1</value></coordinates><team>8564</team><player1>127460</player1><stats><corners>1</corners></stats><id>4964623</id><n>308</n></value><value><event_incident_typefk>867</event_incident_typefk><elapsed>45</elapsed><elapsed_plus>2</elapsed_plus><sortorder>12</sortorder><type>corner</type><subtype>cross_left</subtype><coordinates><value>1</value><value>1</value></coordinates><team>8564</team><player1>41269</player1><stats><corners>1</corners></stats><id>4964632</id><n>312</n></value><value><event_incident_typefk>867</event_incident_typefk><elapsed>57</elapsed><sortorder>1</sortorder><type>corner</type><subtype>cross_left</subtype><coordinates><value>1</value><value>1</value></coordinates><team>8564</team><player1>41269</player1><stats><corners>1</corners></stats><id>4964928</id><n>390</n></value><value><event_incident_typefk>869</event_incident_typefk><elapsed>58</elapsed><sortorder>2</sortorder><type>corner</type><subtype>cross_right</subtype><coordinates><value>45</value><value>1</value></coordinates><team>8564</team><player1>127460</player1><stats><corners>1</corners></stats><id>4964959</id><n>404</n></value><value><event_incident_typefk>871</event_incident_typefk><elapsed>63</elapsed><sortorder>2</sortorder><type>corner</type><subtype>short_left</subtype><coordinates><value>1</value><value>1</value></coordinates><team>8564</team><player1>41269</player1><stats><corners>1</corners></stats><id>4965051</id><n>430</n></value><value><event_incident_typefk>869</event_incident_typefk><elapsed>68</elapsed><sortorder>1</sortorder><type>corner</type><subtype>cross_right</subtype><coordinates><value>1</value><value>69</value></coordinates><team>8533</team><player1>195998</player1><stats><corners>1</corners></stats><id>4965138</id><n>454</n></value><value><event_incident_typefk>869</event_incident_typefk><elapsed>80</elapsed><sortorder>2</sortorder><type>corner</type><subtype>cross_right</subtype><coordinates><value>45</value><value>1</value></coordinates><team>8564</team><player1>127460</player1><stats><corners>1</corners></stats><id>4965345</id><n>489</n></value><value><event_incident_typefk>867</event_incident_typefk><elapsed>89</elapsed><sortorder>1</sortorder><type>corner</type><subtype>cross_left</subtype><coordinates><value>1</value><value>1</value></coordinates><team>8564</team><player1>127460</player1><stats><corners>1</corners></stats><id>4965517</id><n>524</n></value></corner><possession><value><event_incident_typefk>352</event_incident_typefk><elapsed>22</elapsed><comment>62</comment><sortorder>3</sortorder><type>special</type><subtype>possession</subtype><homepos>62</homepos><awaypos>38</awaypos><stats><homepos>62</homepos><awaypos>38</awaypos></stats><id>4964103</id><n>170</n></value><value><event_incident_typefk>352</event_incident_typefk><elapsed>45</elapsed><comment>56</comment><sortorder>2</sortorder><type>special</type><subtype>possession</subtype><homepos>56</homepos><awaypos>44</awaypos><stats><homepos>56</homepos><awaypos>44</awaypos></stats><id>4964590</id><n>295</n></value><value><event_incident_typefk>352</event_incident_typefk><elapsed>67</elapsed><comment>57</comment><sortorder>1</sortorder><type>special</type><subtype>possession</subtype><homepos>57</homepos><awaypos>43</awaypos><stats><homepos>57</homepos><awaypos>43</awaypos></stats><id>4965123</id><n>447</n></value><value><event_incident_typefk>352</event_incident_typefk><elapsed>90</elapsed><elapsed_plus>1</elapsed_plus><comment>54</comment><sortorder>1</sortorder><type>special</type><subtype>possession</subtype><homepos>54</homepos><awaypos>46</awaypos><stats><homepos>54</homepos><awaypos>46</awaypos></stats><id>4965545</id><n>533</n></value></possession></item>