<item><country>Spain</country><league>Primera Division</league><season>2017/2018</season><stage>23</stage><matchId>2580762</matchId><date>2018-02-16 15:00</date><homeTeamId><value>9783</value></homeTeamId><awayTeamId><value>8603</value></awayTeamId><homeTeamFullName><value>Deportivo La Coruna</value></homeTeamFullName><awayTeamFullName><value>Real Betis</value></awayTeamFullName><homeTeamAcronym><value>COR</value></homeTeamAcronym><awayTeamAcronym><value>BET</value></awayTeamAcronym><homeTeamGoal>None</homeTeamGoal><awayTeamGoal>None</awayTeamGoal><homePlayers><value>Ruben Martinez</value><value>Juanfran</value><value>Raul Albentosa</value><value>Eneko Boveda</value><value>Luisinho</value><value>Federico Valverde</value><value>Michael Krohn-Dehli</value><value>Lucas Perez</value><value>Adrian Lopez</value><value>Zakaria Bakkali</value><value>Florin Andone</value></homePlayers><awayPlayers><value>Antonio Adan</value><value>Francis Guerrero</value><value>Aissa Mandi</value><value>Marc Bartra</value><value>Junior Firpo</value><value>Jordi Amat</value><value>Joaquin</value><value>Andres Guardado</value><value>Fabian</value><value>Ryad Boudebouz</value><value>Loren Moron</value></awayPlayers><homePlayersId><value>37656</value><value>103905</value><value>170341</value><value>477471</value><value>115519</value><value>194660</value><value>39215</value><value>45744</value><value>743533</value><value>432463</value><value>599425</value></homePlayersId><awayPlayersId><value>40648</value><value>193223</value><value>195305</value><value>210683</value><value>727088</value><value>743192</value><value>605654</value><value>37824</value><value>31045</value><value>155623</value><value>676536</value></awayPlayersId><homePlayersX><value>1</value><value>2</value><value>4</value><value>6</value><value>8</value><value>4</value><value>6</value><value>3</value><value>5</value><value>7</value><value>5</value></homePlayersX><awayPlayersX><value>1</value><value>1</value><value>3</value><value>5</value><value>9</value><value>7</value><value>3</value><value>5</value><value>7</value><value>4</value><value>6</value></awayPlayersX><homePlayersY><value>1</value><value>3</value><value>3</value><value>3</value><value>3</value><value>6</value><value>6</value><value>8</value><value>8</value><value>8</value><value>11</value></homePlayersY><awayPlayersY><value>1</value><value>3</value><value>3</value><value>3</value><value>3</value><value>3</value><value>7</value><value>7</value><value>7</value><value>10</value><value>10</value></awayPlayersY><goal><value><event_incident_typefk>393</event_incident_typefk><elapsed>54</elapsed><comment>n</comment><sortorder>1</sortorder><type>goal</type><subtype>shot</subtype><goal_type>n</goal_type><coordinates><value>25</value><value>64</value></coordinates><team>8603</team><player1>676536</player1><player2>743192</player2><stats><goals>1</goals><shoton>1</shoton></stats><id>7627030</id><n>332</n></value></goal><shoton><value><event_incident_typefk>135</event_incident_typefk><elapsed>5</elapsed><sortorder>3</sortorder><type>shoton</type><subtype>shot</subtype><coordinates><value>30</value><value>61</value></coordinates><team>8603</team><player1>37824</player1><stats><shoton>1</shoton></stats><id>7626635</id><n>40</n></value><value><event_incident_typefk>61</event_incident_typefk><elapsed>27</elapsed><sortorder>0</sortorder><type>shoton</type><subtype>blocked_shot</subtype><coordinates><value>18</value><value>53</value></coordinates><team>8603</team><player1>155623</player1><stats><blocked>1</blocked></stats><id>7626797</id><n>161</n></value><value><event_incident_typefk>61</event_incident_typefk><elapsed>27</elapsed><sortorder>3</sortorder><type>shoton</type><subtype>blocked_shot</subtype><coordinates><value>17</value><value>61</value></coordinates><team>8603</team><player1>605654</player1><stats><blocked>1</blocked></stats><id>7626800</id><n>164</n></value><value><event_incident_typefk>61</event_incident_typefk><elapsed>37</elapsed><sortorder>0</sortorder><type>shoton</type><subtype>blocked_shot</subtype><coordinates><value>23</value><value>52</value></coordinates><team>8603</team><player1>605654</player1><stats><blocked>1</blocked></stats><id>7626865</id><n>218</n></value><value><event_incident_typefk>1056</event_incident_typefk><elapsed>38</elapsed><sortorder>0</sortorder><type>shoton</type><subtype>direct_freekick</subtype><coordinates><value>21</value><value>55</value></coordinates><team>8603</team><player2>37656</player2><player1>155623</player1><stats><shoton>1</shoton></stats><id>7626876</id><n>230</n></value><value><event_incident_typefk>1061</event_incident_typefk><elapsed>39</elapsed><sortorder>2</sortorder><type>shoton</type><subtype>shot</subtype><coordinates><value>19</value><value>10</value></coordinates><team>9783</team><player2>40648</player2><player1>115519</player1><stats><shoton>1</shoton></stats><id>7626881</id><n>235</n></value><value><event_incident_typefk>876</event_incident_typefk><elapsed>40</elapsed><sortorder>3</sortorder><type>shoton</type><subtype>blocked_header</subtype><coordinates><value>28</value><value>2</value></coordinates><team>9783</team><player1>45744</player1><stats><blocked>1</blocked></stats><id>7626898</id><n>250</n></value><value><event_incident_typefk>1054</event_incident_typefk><elapsed>50</elapsed><sortorder>0</sortorder><type>shoton</type><subtype>distance</subtype><coordinates><value>16</value><value>55</value></coordinates><team>8603</team><player2>37656</player2><player1>155623</player1><stats><shoton>1</shoton></stats><id>7626998</id><n>297</n></value><value><event_incident_typefk>312</event_incident_typefk><elapsed>66</elapsed><sortorder>0</sortorder><type>shoton</type><subtype>deflected</subtype><coordinates><value>24</value><value>54</value></coordinates><team>8603</team><player1>676536</player1><stats><shoton>1</shoton></stats><id>7627108</id><n>384</n></value><value><event_incident_typefk>135</event_incident_typefk><elapsed>70</elapsed><sortorder>2</sortorder><type>shoton</type><subtype>shot</subtype><coordinates><value>37</value><value>8</value></coordinates><team>9783</team><player1>474680</player1><stats><shoton>1</shoton></stats><id>7627141</id><n>405</n></value><value><event_incident_typefk>61</event_incident_typefk><elapsed>73</elapsed><sortorder>0</sortorder><type>shoton</type><subtype>blocked_shot</subtype><coordinates><value>13</value><value>7</value></coordinates><team>9783</team><player1>45744</player1><stats><blocked>1</blocked></stats><id>7627150</id><n>424</n></value><value><event_incident_typefk>311</event_incident_typefk><elapsed>76</elapsed><sortorder>0</sortorder><type>shoton</type><subtype>deflected</subtype><coordinates><value>18</value><value>18</value></coordinates><team>9783</team><player1>474680</player1><stats><shoton>1</shoton></stats><id>7627168</id><n>437</n></value><value><event_incident_typefk>876</event_incident_typefk><elapsed>87</elapsed><sortorder>4</sortorder><type>shoton</type><subtype>blocked_header</subtype><coordinates><value>26</value><value>7</value></coordinates><team>9783</team><player1>477471</player1><stats><blocked>1</blocked></stats><id>7627232</id><n>497</n></value></shoton><shotoff><value><event_incident_typefk>47</event_incident_typefk><elapsed>8</elapsed><sortorder>1</sortorder><type>shotoff</type><subtype>header</subtype><coordinates><value>19</value><value>4</value></coordinates><team>9783</team><player1>599425</player1><stats><shotoff>1</shotoff></stats><id>7626655</id><n>54</n></value><value><event_incident_typefk>113</event_incident_typefk><elapsed>13</elapsed><sortorder>0</sortorder><type>shotoff</type><subtype>post</subtype><coordinates><value>20</value><value>13</value></coordinates><team>9783</team><player1>432463</player1><stats><shotoff>1</shotoff></stats><id>7626693</id><n>93</n></value><value><event_incident_typefk>47</event_incident_typefk><elapsed>21</elapsed><sortorder>1</sortorder><type>shotoff</type><subtype>header</subtype><coordinates><value>25</value><value>61</value></coordinates><team>8603</team><player1>605654</player1><stats><shotoff>1</shotoff></stats><id>7626750</id><n>129</n></value><value><event_incident_typefk>9</event_incident_typefk><elapsed>29</elapsed><sortorder>3</sortorder><type>shotoff</type><subtype>distance</subtype><coordinates><value>17</value><value>57</value></coordinates><team>8603</team><player1>195305</player1><stats><shotoff>1</shotoff></stats><id>7626816</id><n>190</n></value><value><event_incident_typefk>113</event_incident_typefk><elapsed>70</elapsed><sortorder>1</sortorder><type>shotoff</type><subtype>post</subtype><coordinates><value>33</value><value>4</value></coordinates><team>9783</team><player1>599425</player1><stats><shotoff>1</shotoff></stats><id>7627140</id><n>399</n></value><value><event_incident_typefk>81</event_incident_typefk><elapsed>72</elapsed><sortorder>0</sortorder><type>shotoff</type><subtype>direct_freekick</subtype><coordinates><value>22</value><value>14</value></coordinates><team>9783</team><player1>45744</player1><stats><shotoff>1</shotoff></stats><id>7627146</id><n>421</n></value><value><event_incident_typefk>46</event_incident_typefk><elapsed>87</elapsed><sortorder>5</sortorder><type>shotoff</type><subtype>shot</subtype><coordinates><value>26</value><value>6</value></coordinates><team>9783</team><player1>477471</player1><stats><shotoff>1</shotoff></stats><id>7627233</id><n>500</n></value><value><event_incident_typefk>46</event_incident_typefk><elapsed>90</elapsed><elapsed_plus>1</elapsed_plus><sortorder>6</sortorder><type>shotoff</type><subtype>shot</subtype><coordinates><value>14</value><value>7</value></coordinates><team>9783</team><player1>51953</player1><stats><shotoff>1</shotoff></stats><id>7627260</id><n>519</n></value><value><event_incident_typefk>585</event_incident_typefk><elapsed>90</elapsed><elapsed_plus>2</elapsed_plus><sortorder>11</sortorder><type>shotoff</type><subtype>big chance volley</subtype><coordinates><value>29</value><value>4</value></coordinates><team>9783</team><player1>599425</player1><stats><shotoff>1</shotoff></stats><id>7627269</id><n>533</n></value></shotoff><card><value><event_incident_typefk>70</event_incident_typefk><elapsed>43</elapsed><comment>y</comment><sortorder>4</sortorder><type>card</type><card_type>y</card_type><team>9783</team><player1>432463</player1><stats><ycards>1</ycards></stats><id>7626923</id><n>269</n></value><value><event_incident_typefk>70</event_incident_typefk><elapsed>65</elapsed><comment>y</comment><sortorder>1</sortorder><type>card</type><card_type>y</card_type><team>9783</team><player1>477471</player1><stats><ycards>1</ycards></stats><id>7627098</id><n>381</n></value></card><cross><value><event_incident_typefk>7</event_incident_typefk><elapsed>6</elapsed><sortorder>1</sortorder><type>cross</type><subtype>cross</subtype><coordinates><value>43</value><value>19</value></coordinates><team>9783</team><player1>103905</player1><stats><crosses>1</crosses></stats><id>7626638</id><n>43</n></value><value><event_incident_typefk>7</event_incident_typefk><elapsed>7</elapsed><sortorder>1</sortorder><type>cross</type><subtype>cross</subtype><coordinates><value>42</value><value>3</value></coordinates><team>9783</team><player1>103905</player1><stats><crosses>1</crosses></stats><id>7626647</id><n>48</n></value><value><event_incident_typefk>7</event_incident_typefk><elapsed>8</elapsed><sortorder>0</sortorder><type>cross</type><subtype>cross</subtype><coordinates><value>4</value><value>3</value></coordinates><team>9783</team><player1>115519</player1><stats><crosses>1</crosses></stats><id>7626652</id><n>52</n></value><value><event_incident_typefk>939</event_incident_typefk><elapsed>9</elapsed><sortorder>1</sortorder><type>cross</type><subtype>cross</subtype><coordinates><value>7</value><value>5</value></coordinates><team>9783</team><player1>45744</player1><stats><crosses>1</crosses></stats><id>7626665</id><n>69</n></value><value><event_incident_typefk>7</event_incident_typefk><elapsed>11</elapsed><sortorder>2</sortorder><type>cross</type><subtype>cross</subtype><coordinates><value>7</value><value>67</value></coordinates><team>8603</team><player1>37824</player1><stats><crosses>1</crosses></stats><id>7626686</id><n>83</n></value><value><event_incident_typefk>770</event_incident_typefk><elapsed>17</elapsed><sortorder>0</sortorder><type>cross</type><subtype>cross</subtype><coordinates><value>5</value><value>66</value></coordinates><team>8603</team><player1>727088</player1><stats><crosses>1</crosses></stats><id>7626716</id><n>103</n></value><value><event_incident_typefk>7</event_incident_typefk><elapsed>21</elapsed><sortorder>0</sortorder><type>cross</type><subtype>cross</subtype><coordinates><value>40</value><value>55</value></coordinates><team>8603</team><player1>37824</player1><stats><crosses>1</crosses></stats><id>7626748</id><n>124</n></value><value><event_incident_typefk>7</event_incident_typefk><elapsed>22</elapsed><sortorder>0</sortorder><type>cross</type><subtype>cross</subtype><coordinates><value>42</value><value>65</value></coordinates><team>8603</team><player1>743192</player1><stats><crosses>1</crosses></stats><id>7626763</id><n>137</n></value><value><event_incident_typefk>7</event_incident_typefk><elapsed>23</elapsed><sortorder>0</sortorder><type>cross</type><subtype>cross</subtype><coordinates><value>36</value><value>15</value></coordinates><team>9783</team><player1>194660</player1><stats><crosses>1</crosses></stats><id>7626771</id><n>142</n></value><value><event_incident_typefk>7</event_incident_typefk><elapsed>23</elapsed><sortorder>2</sortorder><type>cross</type><subtype>cross</subtype><coordinates><value>5</value><value>9</value></coordinates><team>9783</team><player1>432463</player1><stats><crosses>1</crosses></stats><id>7626773</id><n>146</n></value><value><event_incident_typefk>7</event_incident_typefk><elapsed>29</elapsed><sortorder>0</sortorder><type>cross</type><subtype>cross</subtype><coordinates><value>42</value><value>8</value></coordinates><team>9783</team><player1>103905</player1><stats><crosses>1</crosses></stats><id>7626813</id><n>182</n></value><value><event_incident_typefk>770</event_incident_typefk><elapsed>33</elapsed><sortorder>0</sortorder><type>cross</type><subtype>cross</subtype><coordinates><value>6</value><value>65</value></coordinates><team>8603</team><player1>727088</player1><stats><crosses>1</crosses></stats><id>7626839</id><n>203</n></value><value><event_incident_typefk>7</event_incident_typefk><elapsed>40</elapsed><sortorder>0</sortorder><type>cross</type><subtype>cross</subtype><coordinates><value>5</value><value>7</value></coordinates><team>9783</team><player1>115519</player1><stats><crosses>1</crosses></stats><id>7626885</id><n>241</n></value><value><event_incident_typefk>7</event_incident_typefk><elapsed>40</elapsed><sortorder>2</sortorder><type>cross</type><subtype>cross</subtype><coordinates><value>5</value><value>4</value></coordinates><team>9783</team><player1>432463</player1><stats><crosses>1</crosses></stats><id>7626893</id><n>247</n></value><value><event_incident_typefk>7</event_incident_typefk><elapsed>43</elapsed><sortorder>1</sortorder><type>cross</type><subtype>cross</subtype><coordinates><value>43</value><value>17</value></coordinates><team>9783</team><player1>103905</player1><stats><crosses>1</crosses></stats><id>7626918</id><n>262</n></value><value><event_incident_typefk>7</event_incident_typefk><elapsed>46</elapsed><sortorder>3</sortorder><type>cross</type><subtype>cross</subtype><coordinates><value>6</value><value>8</value></coordinates><team>9783</team><player1>194660</player1><stats><crosses>1</crosses></stats><id>7626979</id><n>289</n></value><value><event_incident_typefk>7</event_incident_typefk><elapsed>49</elapsed><sortorder>0</sortorder><type>cross</type><subtype>cross</subtype><coordinates><value>12</value><value>49</value></coordinates><team>8603</team><player1>605654</player1><stats><crosses>1</crosses></stats><id>7626994</id><n>293</n></value><value><event_incident_typefk>7</event_incident_typefk><elapsed>53</elapsed><sortorder>0</sortorder><type>cross</type><subtype>cross</subtype><coordinates><value>4</value><value>61</value></coordinates><team>8603</team><player1>605654</player1><stats><crosses>1</crosses></stats><id>7627020</id><n>310</n></value><value><event_incident_typefk>749</event_incident_typefk><elapsed>54</elapsed><sortorder>0</sortorder><type>cross</type><subtype>cross</subtype><coordinates><value>41</value><value>58</value></coordinates><team>8603</team><player1>743192</player1><stats><crosses>1</crosses></stats><id>7627028</id><n>334</n></value><value><event_incident_typefk>7</event_incident_typefk><elapsed>56</elapsed><sortorder>0</sortorder><type>cross</type><subtype>cross</subtype><coordinates><value>40</value><value>4</value></coordinates><team>9783</team><player1>103905</player1><stats><crosses>1</crosses></stats><id>7627044</id><n>337</n></value><value><event_incident_typefk>7</event_incident_typefk><elapsed>56</elapsed><sortorder>2</sortorder><type>cross</type><subtype>cross</subtype><coordinates><value>5</value><value>4</value></coordinates><team>9783</team><player1>115519</player1><stats><crosses>1</crosses></stats><id>7627047</id><n>344</n></value><value><event_incident_typefk>7</event_incident_typefk><elapsed>56</elapsed><sortorder>4</sortorder><type>cross</type><subtype>cross</subtype><coordinates><value>6</value><value>8</value></coordinates><team>9783</team><player1>194660</player1><stats><crosses>1</crosses></stats><id>7627049</id><n>348</n></value><value><event_incident_typefk>7</event_incident_typefk><elapsed>68</elapsed><sortorder>0</sortorder><type>cross</type><subtype>cross</subtype><coordinates><value>5</value><value>66</value></coordinates><team>8603</team><player1>676536</player1><stats><crosses>1</crosses></stats><id>7627119</id><n>387</n></value><value><event_incident_typefk>7</event_incident_typefk><elapsed>82</elapsed><sortorder>0</sortorder><type>cross</type><subtype>cross</subtype><coordinates><value>40</value><value>9</value></coordinates><team>9783</team><player1>194660</player1><stats><crosses>1</crosses></stats><id>7627205</id><n>470</n></value><value><event_incident_typefk>7</event_incident_typefk><elapsed>86</elapsed><sortorder>0</sortorder><type>cross</type><subtype>cross</subtype><coordinates><value>41</value><value>4</value></coordinates><team>9783</team><player1>599425</player1><stats><crosses>1</crosses></stats><id>7627225</id><n>482</n></value><value><event_incident_typefk>770</event_incident_typefk><elapsed>87</elapsed><sortorder>0</sortorder><type>cross</type><subtype>cross</subtype><coordinates><value>4</value><value>7</value></coordinates><team>9783</team><player1>194660</player1><stats><crosses>1</crosses></stats><id>7627227</id><n>487</n></value><value><event_incident_typefk>7</event_incident_typefk><elapsed>87</elapsed><sortorder>1</sortorder><type>cross</type><subtype>cross</subtype><coordinates><value>4</value><value>4</value></coordinates><team>9783</team><player1>194660</player1><stats><crosses>1</crosses></stats><id>7627228</id><n>488</n></value><value><event_incident_typefk>7</event_incident_typefk><elapsed>90</elapsed><sortorder>1</sortorder><type>cross</type><subtype>cross</subtype><coordinates><value>42</value><value>14</value></coordinates><team>9783</team><player1>103905</player1><stats><crosses>1</crosses></stats><id>7627251</id><n>510</n></value><value><event_incident_typefk>7</event_incident_typefk><elapsed>90</elapsed><sortorder>4</sortorder><type>cross</type><subtype>cross</subtype><coordinates><value>41</value><value>2</value></coordinates><team>9783</team><player1>103905</player1><stats><crosses>1</crosses></stats><id>7627255</id><n>514</n></value><value><event_incident_typefk>7</event_incident_typefk><elapsed>90</elapsed><elapsed_plus>1</elapsed_plus><sortorder>10</sortorder><type>cross</type><subtype>cross</subtype><coordinates><value>4</value><value>9</value></coordinates><team>9783</team><player1>115519</player1><stats><crosses>1</crosses></stats><id>7627267</id><n>530</n></value><value><event_incident_typefk>770</event_incident_typefk><elapsed>90</elapsed><elapsed_plus>2</elapsed_plus><sortorder>13</sortorder><type>cross</type><subtype>cross</subtype><coordinates><value>42</value><value>11</value></coordinates><team>9783</team><player1>599425</player1><stats><crosses>1</crosses></stats><id>7627272</id><n>540</n></value></cross><corner><value><event_incident_typefk>867</event_incident_typefk><elapsed>10</elapsed><sortorder>0</sortorder><type>corner</type><subtype>cross_left</subtype><coordinates><value>1</value><value>1</value></coordinates><team>9783</team><player1>39215</player1><stats><corners>1</corners><crosses>1</crosses></stats><id>7626668</id><n>70</n></value><value><event_incident_typefk>869</event_incident_typefk><elapsed>25</elapsed><sortorder>0</sortorder><type>corner</type><subtype>cross_right</subtype><coordinates><value>45</value><value>1</value></coordinates><team>9783</team><player1>45744</player1><stats><corners>1</corners><crosses>1</crosses></stats><id>7626780</id><n>208</n></value><value><event_incident_typefk>869</event_incident_typefk><elapsed>34</elapsed><sortorder>1</sortorder><type>corner</type><subtype>cross_right</subtype><coordinates><value>45</value><value>1</value></coordinates><team>9783</team><player1>194660</player1><stats><corners>1</corners><crosses>1</crosses></stats><id>7626846</id><n>207</n></value><value><event_incident_typefk>867</event_incident_typefk><elapsed>39</elapsed><sortorder>0</sortorder><type>corner</type><subtype>cross_left</subtype><coordinates><value>1</value><value>1</value></coordinates><team>9783</team><player1>432463</player1><stats><corners>1</corners><crosses>1</crosses></stats><id>7626879</id><n>231</n></value><value><event_incident_typefk>869</event_incident_typefk><elapsed>41</elapsed><sortorder>0</sortorder><type>corner</type><subtype>cross_right</subtype><coordinates><value>45</value><value>1</value></coordinates><team>9783</team><player1>194660</player1><stats><corners>1</corners><crosses>1</crosses></stats><id>7626900</id><n>251</n></value><value><event_incident_typefk>867</event_incident_typefk><elapsed>51</elapsed><sortorder>2</sortorder><type>corner</type><subtype>cross_left</subtype><coordinates><value>45</value><value>69</value></coordinates><team>8603</team><player1>37824</player1><stats><corners>1</corners><crosses>1</crosses></stats><id>7627004</id><n>302</n></value><value><event_incident_typefk>869</event_incident_typefk><elapsed>62</elapsed><sortorder>3</sortorder><type>corner</type><subtype>cross_right</subtype><coordinates><value>45</value><value>1</value></coordinates><team>9783</team><player1>194660</player1><stats><corners>1</corners><crosses>1</crosses></stats><id>7627084</id><n>364</n></value><value><event_incident_typefk>867</event_incident_typefk><elapsed>78</elapsed><sortorder>2</sortorder><type>corner</type><subtype>cross_left</subtype><coordinates><value>1</value><value>1</value></coordinates><team>9783</team><player1>474680</player1><stats><corners>1</corners><crosses>1</crosses></stats><id>7627184</id><n>459</n></value><value><event_incident_typefk>867</event_incident_typefk><elapsed>87</elapsed><sortorder>3</sortorder><type>corner</type><subtype>cross_left</subtype><coordinates><value>1</value><value>1</value></coordinates><team>9783</team><player1>194660</player1><stats><corners>1</corners><crosses>1</crosses></stats><id>7627231</id><n>492</n></value></corner><possession><value><event_incident_typefk>352</event_incident_typefk><elapsed>5</elapsed><comment>50</comment><sortorder>1</sortorder><type>special</type><subtype>possession</subtype><homepos>50</homepos><awaypos>50</awaypos><stats><homepos>50</homepos><awaypos>50</awaypos></stats><id>7626631</id><n>36</n></value><value><event_incident_typefk>352</event_incident_typefk><elapsed>10</elapsed><comment>50</comment><sortorder>2</sortorder><type>special</type><subtype>possession</subtype><homepos>50</homepos><awaypos>50</awaypos><stats><homepos>50</homepos><awaypos>50</awaypos></stats><id>7626673</id><n>556</n></value><value><event_incident_typefk>352</event_incident_typefk><elapsed>15</elapsed><comment>45</comment><sortorder>0</sortorder><type>special</type><subtype>possession</subtype><homepos>45</homepos><awaypos>55</awaypos><stats><homepos>45</homepos><awaypos>55</awaypos></stats><id>7626706</id><n>100</n></value><value><event_incident_typefk>352</event_incident_typefk><elapsed>20</elapsed><comment>37</comment><sortorder>0</sortorder><type>special</type><subtype>possession</subtype><homepos>37</homepos><awaypos>63</awaypos><stats><homepos>37</homepos><awaypos>63</awaypos></stats><id>7626736</id><n>120</n></value><value><event_incident_typefk>352</event_incident_typefk><elapsed>25</elapsed><comment>40</comment><sortorder>3</sortorder><type>special</type><subtype>possession</subtype><homepos>40</homepos><awaypos>60</awaypos><stats><homepos>40</homepos><awaypos>60</awaypos></stats><id>7626794</id><n>158</n></value><value><event_incident_typefk>352</event_incident_typefk><elapsed>30</elapsed><comment>42</comment><sortorder>1</sortorder><type>special</type><subtype>possession</subtype><homepos>42</homepos><awaypos>58</awaypos><stats><homepos>42</homepos><awaypos>58</awaypos></stats><id>7626823</id><n>196</n></value><value><event_incident_typefk>352</event_incident_typefk><elapsed>35</elapsed><comment>42</comment><sortorder>0</sortorder><type>special</type><subtype>possession</subtype><homepos>42</homepos><awaypos>58</awaypos><stats><homepos>42</homepos><awaypos>58</awaypos></stats><id>7626853</id><n>209</n></value><value><event_incident_typefk>352</event_incident_typefk><elapsed>40</elapsed><comment>44</comment><sortorder>4</sortorder><type>special</type><subtype>possession</subtype><homepos>44</homepos><awaypos>56</awaypos><stats><homepos>44</homepos><awaypos>56</awaypos></stats><id>7626907</id><n>254</n></value><value><event_incident_typefk>352</event_incident_typefk><elapsed>45</elapsed><comment>42</comment><sortorder>0</sortorder><type>special</type><subtype>possession</subtype><homepos>42</homepos><awaypos>58</awaypos><stats><homepos>42</homepos><awaypos>58</awaypos></stats><id>7626925</id><n>267</n></value><value><event_incident_typefk>352</event_incident_typefk><elapsed>45</elapsed><elapsed_plus>2</elapsed_plus><comment>41</comment><sortorder>4</sortorder><type>special</type><subtype>possession</subtype><homepos>41</homepos><awaypos>59</awaypos><stats><homepos>41</homepos><awaypos>59</awaypos></stats><id>7626942</id><n>276</n></value><value><event_incident_typefk>352</event_incident_typefk><elapsed>50</elapsed><comment>41</comment><sortorder>1</sortorder><type>special</type><subtype>possession</subtype><homepos>41</homepos><awaypos>59</awaypos><stats><homepos>41</homepos><awaypos>59</awaypos></stats><id>7626999</id><n>299</n></value><value><event_incident_typefk>352</event_incident_typefk><elapsed>55</elapsed><comment>39</comment><sortorder>0</sortorder><type>special</type><subtype>possession</subtype><homepos>39</homepos><awaypos>61</awaypos><stats><homepos>39</homepos><awaypos>61</awaypos></stats><id>7627037</id><n>327</n></value><value><event_incident_typefk>352</event_incident_typefk><elapsed>60</elapsed><comment>41</comment><sortorder>1</sortorder><type>special</type><subtype>possession</subtype><homepos>41</homepos><awaypos>59</awaypos><stats><homepos>41</homepos><awaypos>59</awaypos></stats><id>7627066</id><n>355</n></value><value><event_incident_typefk>352</event_incident_typefk><elapsed>65</elapsed><comment>42</comment><sortorder>2</sortorder><type>special</type><subtype>possession</subtype><homepos>42</homepos><awaypos>58</awaypos><stats><homepos>42</homepos><awaypos>58</awaypos></stats><id>7627100</id><n>382</n></value><value><event_incident_typefk>352</event_incident_typefk><elapsed>70</elapsed><comment>43</comment><sortorder>3</sortorder><type>special</type><subtype>possession</subtype><homepos>43</homepos><awaypos>57</awaypos><stats><homepos>43</homepos><awaypos>57</awaypos></stats><id>7627134</id><n>555</n></value><value><event_incident_typefk>352</event_incident_typefk><elapsed>75</elapsed><comment>43</comment><sortorder>2</sortorder><type>special</type><subtype>possession</subtype><homepos>43</homepos><awaypos>57</awaypos><stats><homepos>43</homepos><awaypos>57</awaypos></stats><id>7627163</id><n>435</n></value><value><event_incident_typefk>352</event_incident_typefk><elapsed>80</elapsed><comment>44</comment><sortorder>0</sortorder><type>special</type><subtype>possession</subtype><homepos>44</homepos><awaypos>56</awaypos><stats><homepos>44</homepos><awaypos>56</awaypos></stats><id>7627194</id><n>468</n></value><value><event_incident_typefk>352</event_incident_typefk><elapsed>85</elapsed><comment>43</comment><sortorder>0</sortorder><type>special</type><subtype>possession</subtype><homepos>43</homepos><awaypos>57</awaypos><stats><homepos>43</homepos><awaypos>57</awaypos></stats><id>7627221</id><n>478</n></value><value><event_incident_typefk>352</event_incident_typefk><elapsed>90</elapsed><comment>43</comment><sortorder>0</sortorder><type>special</type><subtype>possession</subtype><homepos>43</homepos><awaypos>57</awaypos><stats><homepos>43</homepos><awaypos>57</awaypos></stats><id>7627248</id><n>508</n></value><value><event_incident_typefk>352</event_incident_typefk><elapsed>90</elapsed><elapsed_plus>5</elapsed_plus><comment>44</comment><sortorder>21</sortorder><type>special</type><subtype>possession</subtype><homepos>44</homepos><awaypos>56</awaypos><stats><homepos>44</homepos><awaypos>56</awaypos></stats><id>7627287</id><n>552</n></value></possession></item>