<item><country>Spain</country><league>Primera Division</league><season>2018/2019</season><stage>2</stage><matchId>2844467</matchId><date>2018-08-27 16:00</date><homeTeamId><value>8302</value></homeTeamId><awayTeamId><value>10205</value></awayTeamId><homeTeamFullName><value>Sevilla</value></homeTeamFullName><awayTeamFullName><value>Villarreal</value></awayTeamFullName><homeTeamAcronym><value>SEV</value></homeTeamAcronym><awayTeamAcronym><value>VIL</value></awayTeamAcronym><homeTeamGoal>None</homeTeamGoal><awayTeamGoal>None</awayTeamGoal><homePlayers><value>Tomas Vaclik</value><value>Gabriel Mercado</value><value>Simon Kjaer</value><value>Sergi Gomez</value><value>Jesus Navas</value><value>Ever Banega</value><value>Roque Mesa</value><value>Sergio Escudero</value><value>Pablo Sarabia</value><value>Andre Silva</value><value>Franco Vazquez</value></homePlayers><awayPlayers><value>Sergio Asenjo</value><value>Mario Gaspar</value><value>Victor Ruiz</value><value>Alvaro Gonzalez</value><value>Alfonso Pedraza</value><value>Pablo Fornals</value><value>Manuel Trigueros</value><value>Santiago Caseres</value><value>Santi Cazorla</value><value>Gerard Moreno</value><value>Karl Toko Ekambi</value></awayPlayers><homePlayersId><value>156175</value><value>358148</value><value>35112</value><value>113668</value><value>292262</value><value>108568</value><value>33991</value><value>209950</value><value>388523</value><value>240054</value><value>270774</value></homePlayersId><awayPlayersId><value>96623</value><value>183185</value><value>257855</value><value>182921</value><value>629594</value><value>797927</value><value>683450</value><value>268282</value><value>37436</value><value>246438</value><value>426906</value></awayPlayersId><homePlayersX><value>1</value><value>3</value><value>5</value><value>7</value><value>2</value><value>4</value><value>6</value><value>8</value><value>3</value><value>5</value><value>7</value></homePlayersX><awayPlayersX><value>1</value><value>2</value><value>4</value><value>6</value><value>8</value><value>2</value><value>4</value><value>6</value><value>8</value><value>4</value><value>6</value></awayPlayersX><homePlayersY><value>1</value><value>3</value><value>3</value><value>3</value><value>7</value><value>7</value><value>7</value><value>7</value><value>10</value><value>10</value><value>10</value></homePlayersY><awayPlayersY><value>1</value><value>3</value><value>3</value><value>3</value><value>3</value><value>7</value><value>7</value><value>7</value><value>7</value><value>10</value><value>10</value></awayPlayersY><goal></goal><shoton><value><event_incident_typefk>61</event_incident_typefk><elapsed>7</elapsed><sortorder>2</sortorder><type>shoton</type><subtype>blocked_shot</subtype><coordinates><value>27</value><value>9</value></coordinates><team>8302</team><player1>292262</player1><stats><blocked>1</blocked></stats><id>8308892</id><n>52</n></value><value><event_incident_typefk>1062</event_incident_typefk><elapsed>8</elapsed><sortorder>1</sortorder><type>shoton</type><subtype>distance</subtype><coordinates><value>19</value><value>15</value></coordinates><team>8302</team><player2>96623</player2><player1>292262</player1><stats><shoton>1</shoton></stats><id>8308907</id><n>56</n></value><value><event_incident_typefk>1055</event_incident_typefk><elapsed>12</elapsed><sortorder>1</sortorder><type>shoton</type><subtype>volley</subtype><coordinates><value>14</value><value>5</value></coordinates><team>8302</team><player2>96623</player2><player1>209950</player1><stats><shoton>1</shoton></stats><id>8308981</id><n>81</n></value><value><event_incident_typefk>494</event_incident_typefk><elapsed>23</elapsed><sortorder>0</sortorder><type>shoton</type><subtype>blocked_shot</subtype><coordinates><value>27</value><value>17</value></coordinates><team>8302</team><player1>108568</player1><stats><blocked>1</blocked></stats><id>8309144</id><n>154</n></value><value><event_incident_typefk>61</event_incident_typefk><elapsed>24</elapsed><sortorder>2</sortorder><type>shoton</type><subtype>blocked_shot</subtype><coordinates><value>13</value><value>8</value></coordinates><team>8302</team><player1>209950</player1><stats><blocked>1</blocked></stats><id>8309158</id><n>163</n></value><value><event_incident_typefk>1052</event_incident_typefk><elapsed>28</elapsed><sortorder>1</sortorder><type>shoton</type><subtype>deflected</subtype><coordinates><value>13</value><value>57</value></coordinates><team>10205</team><player2>156175</player2><player1>683450</player1><stats><shoton>1</shoton></stats><id>8309214</id><n>189</n></value><value><event_incident_typefk>61</event_incident_typefk><elapsed>29</elapsed><sortorder>0</sortorder><type>shoton</type><subtype>blocked_shot</subtype><coordinates><value>27</value><value>58</value></coordinates><team>10205</team><player1>683450</player1><stats><blocked>1</blocked></stats><id>8309219</id><n>191</n></value><value><event_incident_typefk>61</event_incident_typefk><elapsed>39</elapsed><sortorder>0</sortorder><type>shoton</type><subtype>blocked_shot</subtype><coordinates><value>15</value><value>7</value></coordinates><team>8302</team><player1>270774</player1><stats><blocked>1</blocked></stats><id>8309316</id><n>244</n></value><value><event_incident_typefk>61</event_incident_typefk><elapsed>39</elapsed><sortorder>2</sortorder><type>shoton</type><subtype>blocked_shot</subtype><coordinates><value>21</value><value>55</value></coordinates><team>10205</team><player1>37436</player1><stats><blocked>1</blocked></stats><id>8309319</id><n>250</n></value><value><event_incident_typefk>1054</event_incident_typefk><elapsed>39</elapsed><sortorder>3</sortorder><type>shoton</type><subtype>distance</subtype><coordinates><value>29</value><value>56</value></coordinates><team>10205</team><player2>156175</player2><player1>426906</player1><stats><shoton>1</shoton></stats><id>8309321</id><n>251</n></value><value><event_incident_typefk>611</event_incident_typefk><elapsed>41</elapsed><sortorder>1</sortorder><type>shoton</type><subtype>big chance shot</subtype><coordinates><value>13</value><value>64</value></coordinates><team>10205</team><player2>156175</player2><player1>426906</player1><stats><shoton>1</shoton></stats><id>8309336</id><n>260</n></value><value><event_incident_typefk>1062</event_incident_typefk><elapsed>44</elapsed><sortorder>0</sortorder><type>shoton</type><subtype>distance</subtype><coordinates><value>33</value><value>57</value></coordinates><team>10205</team><player2>156175</player2><player1>426906</player1><stats><shoton>1</shoton></stats><id>8309352</id><n>271</n></value><value><event_incident_typefk>1062</event_incident_typefk><elapsed>49</elapsed><sortorder>0</sortorder><type>shoton</type><subtype>distance</subtype><coordinates><value>39</value><value>62</value></coordinates><team>10205</team><player2>156175</player2><player1>629594</player1><stats><shoton>1</shoton></stats><id>8309416</id><n>328</n></value><value><event_incident_typefk>61</event_incident_typefk><elapsed>51</elapsed><sortorder>2</sortorder><type>shoton</type><subtype>blocked_shot</subtype><coordinates><value>26</value><value>62</value></coordinates><team>10205</team><player1>246438</player1><stats><blocked>1</blocked></stats><id>8309433</id><n>343</n></value><value><event_incident_typefk>61</event_incident_typefk><elapsed>52</elapsed><sortorder>3</sortorder><type>shoton</type><subtype>blocked_shot</subtype><coordinates><value>33</value><value>65</value></coordinates><team>10205</team><player1>683450</player1><stats><blocked>1</blocked></stats><id>8309446</id><n>352</n></value><value><event_incident_typefk>61</event_incident_typefk><elapsed>60</elapsed><sortorder>0</sortorder><type>shoton</type><subtype>blocked_shot</subtype><coordinates><value>25</value><value>12</value></coordinates><team>8302</team><player1>240054</player1><stats><blocked>1</blocked></stats><id>8309495</id><n>409</n></value><value><event_incident_typefk>611</event_incident_typefk><elapsed>68</elapsed><sortorder>3</sortorder><type>shoton</type><subtype>big chance shot</subtype><coordinates><value>15</value><value>63</value></coordinates><team>10205</team><player2>156175</player2><player1>166648</player1><stats><shoton>1</shoton></stats><id>8309544</id><n>442</n></value><value><event_incident_typefk>61</event_incident_typefk><elapsed>74</elapsed><sortorder>2</sortorder><type>shoton</type><subtype>blocked_shot</subtype><coordinates><value>30</value><value>12</value></coordinates><team>8302</team><player1>33991</player1><stats><blocked>1</blocked></stats><id>8309587</id><n>475</n></value><value><event_incident_typefk>609</event_incident_typefk><elapsed>90</elapsed><sortorder>1</sortorder><type>shoton</type><subtype>big chance shot</subtype><coordinates><value>22</value><value>3</value></coordinates><team>8302</team><player2>96623</player2><player1>388523</player1><stats><shoton>1</shoton></stats><id>8309791</id><n>532</n></value><value><event_incident_typefk>61</event_incident_typefk><elapsed>90</elapsed><elapsed_plus>3</elapsed_plus><sortorder>14</sortorder><type>shoton</type><subtype>blocked_shot</subtype><coordinates><value>15</value><value>8</value></coordinates><team>8302</team><player1>189192</player1><stats><blocked>1</blocked></stats><id>8309807</id><n>561</n></value></shoton><shotoff><value><event_incident_typefk>587</event_incident_typefk><elapsed>19</elapsed><sortorder>1</sortorder><type>shotoff</type><subtype>big chance shot</subtype><coordinates><value>28</value><value>9</value></coordinates><team>8302</team><player1>388523</player1><stats><shotoff>1</shotoff></stats><id>8309078</id><n>134</n></value><value><event_incident_typefk>53</event_incident_typefk><elapsed>25</elapsed><sortorder>3</sortorder><type>shotoff</type><subtype>volley</subtype><coordinates><value>34</value><value>2</value></coordinates><team>8302</team><player1>33991</player1><stats><shotoff>1</shotoff></stats><id>8309174</id><n>177</n></value><value><event_incident_typefk>9</event_incident_typefk><elapsed>47</elapsed><sortorder>1</sortorder><type>shotoff</type><subtype>distance</subtype><coordinates><value>26</value><value>17</value></coordinates><team>8302</team><player1>388523</player1><stats><shotoff>1</shotoff></stats><id>8309405</id><n>313</n></value><value><event_incident_typefk>53</event_incident_typefk><elapsed>49</elapsed><sortorder>1</sortorder><type>shotoff</type><subtype>volley</subtype><coordinates><value>22</value><value>55</value></coordinates><team>10205</team><player1>37436</player1><stats><shotoff>1</shotoff></stats><id>8309418</id><n>330</n></value><value><event_incident_typefk>9</event_incident_typefk><elapsed>53</elapsed><sortorder>5</sortorder><type>shotoff</type><subtype>distance</subtype><coordinates><value>32</value><value>13</value></coordinates><team>8302</team><player1>388523</player1><stats><shotoff>1</shotoff></stats><id>8309456</id><n>366</n></value><value><event_incident_typefk>9</event_incident_typefk><elapsed>57</elapsed><sortorder>4</sortorder><type>shotoff</type><subtype>distance</subtype><coordinates><value>21</value><value>53</value></coordinates><team>10205</team><player1>268282</player1><stats><shotoff>1</shotoff></stats><id>8309479</id><n>392</n></value><value><event_incident_typefk>743</event_incident_typefk><elapsed>60</elapsed><sortorder>2</sortorder><type>shotoff</type><subtype>miss_kick</subtype><coordinates><value>13</value><value>62</value></coordinates><team>10205</team><player1>683450</player1><id>8309499</id><n>415</n></value><value><event_incident_typefk>590</event_incident_typefk><elapsed>90</elapsed><elapsed_plus>1</elapsed_plus><sortorder>5</sortorder><type>shotoff</type><subtype>big chance post</subtype><coordinates><value>15</value><value>5</value></coordinates><team>8302</team><player1>210184</player1><stats><shotoff>1</shotoff></stats><id>8309795</id><n>543</n></value></shotoff><card><value><event_incident_typefk>203</event_incident_typefk><elapsed>5</elapsed><comment>y</comment><sortorder>5</sortorder><type>card</type><subtype>emergency_brake</subtype><card_type>y</card_type><team>10205</team><player1>183185</player1><stats><ycards>1</ycards></stats><id>8308849</id><n>62</n></value><value><event_incident_typefk>70</event_incident_typefk><elapsed>44</elapsed><comment>y</comment><sortorder>2</sortorder><type>card</type><card_type>y</card_type><team>8302</team><player1>113668</player1><stats><ycards>1</ycards></stats><id>8309356</id><n>276</n></value><value><event_incident_typefk>79</event_incident_typefk><elapsed>81</elapsed><comment>y</comment><sortorder>2</sortorder><type>card</type><subtype>verbal_abuse</subtype><card_type>y</card_type><team>8302</team><player1>240054</player1><stats><ycards>1</ycards></stats><id>8309624</id><n>503</n></value><value><event_incident_typefk>70</event_incident_typefk><elapsed>88</elapsed><comment>y</comment><sortorder>1</sortorder><type>card</type><card_type>y</card_type><team>10205</team><player1>160844</player1><stats><ycards>1</ycards></stats><id>8309653</id><n>522</n></value><value><event_incident_typefk>70</event_incident_typefk><elapsed>90</elapsed><elapsed_plus>2</elapsed_plus><comment>y</comment><sortorder>12</sortorder><type>card</type><card_type>y</card_type><team>8302</team><player1>35112</player1><stats><ycards>1</ycards></stats><id>8309805</id><n>556</n></value></card><cross><value><event_incident_typefk>770</event_incident_typefk><elapsed>4</elapsed><sortorder>2</sortorder><type>cross</type><subtype>cross</subtype><coordinates><value>6</value><value>69</value></coordinates><team>10205</team><player1>37436</player1><stats><crosses>1</crosses></stats><id>8308805</id><n>28</n></value><value><event_incident_typefk>770</event_incident_typefk><elapsed>7</elapsed><sortorder>0</sortorder><type>cross</type><subtype>cross</subtype><coordinates><value>40</value><value>2</value></coordinates><team>8302</team><player1>33991</player1><stats><crosses>1</crosses></stats><id>8308876</id><n>47</n></value><value><event_incident_typefk>7</event_incident_typefk><elapsed>12</elapsed><sortorder>0</sortorder><type>cross</type><subtype>cross</subtype><coordinates><value>41</value><value>4</value></coordinates><team>8302</team><player1>33991</player1><stats><crosses>1</crosses></stats><id>8308976</id><n>79</n></value><value><event_incident_typefk>7</event_incident_typefk><elapsed>13</elapsed><sortorder>1</sortorder><type>cross</type><subtype>cross</subtype><coordinates><value>42</value><value>13</value></coordinates><team>8302</team><player1>33991</player1><stats><crosses>1</crosses></stats><id>8308995</id><n>85</n></value><value><event_incident_typefk>7</event_incident_typefk><elapsed>17</elapsed><sortorder>2</sortorder><type>cross</type><subtype>cross</subtype><coordinates><value>39</value><value>16</value></coordinates><team>8302</team><player1>33991</player1><stats><crosses>1</crosses></stats><id>8309042</id><n>117</n></value><value><event_incident_typefk>7</event_incident_typefk><elapsed>17</elapsed><sortorder>4</sortorder><type>cross</type><subtype>cross</subtype><coordinates><value>11</value><value>16</value></coordinates><team>8302</team><player1>209950</player1><stats><crosses>1</crosses></stats><id>8309049</id><n>122</n></value><value><event_incident_typefk>7</event_incident_typefk><elapsed>24</elapsed><sortorder>1</sortorder><type>cross</type><subtype>cross</subtype><coordinates><value>42</value><value>13</value></coordinates><team>8302</team><player1>33991</player1><stats><crosses>1</crosses></stats><id>8309154</id><n>159</n></value><value><event_incident_typefk>1095</event_incident_typefk><elapsed>24</elapsed><sortorder>3</sortorder><type>throwin</type><subtype>cross</subtype><team>8302</team><stats><throwin>1</throwin></stats><id>8309159</id><n>164</n></value><value><event_incident_typefk>7</event_incident_typefk><elapsed>25</elapsed><sortorder>2</sortorder><type>cross</type><subtype>cross</subtype><coordinates><value>7</value><value>15</value></coordinates><team>8302</team><player1>209950</player1><stats><crosses>1</crosses></stats><id>8309171</id><n>174</n></value><value><event_incident_typefk>770</event_incident_typefk><elapsed>27</elapsed><sortorder>0</sortorder><type>cross</type><subtype>cross</subtype><coordinates><value>5</value><value>68</value></coordinates><team>10205</team><player1>426906</player1><stats><crosses>1</crosses></stats><id>8309194</id><n>183</n></value><value><event_incident_typefk>7</event_incident_typefk><elapsed>33</elapsed><sortorder>2</sortorder><type>cross</type><subtype>cross</subtype><coordinates><value>37</value><value>15</value></coordinates><team>8302</team><player1>108568</player1><stats><crosses>1</crosses></stats><id>8309270</id><n>205</n></value><value><event_incident_typefk>7</event_incident_typefk><elapsed>38</elapsed><sortorder>1</sortorder><type>cross</type><subtype>cross</subtype><coordinates><value>42</value><value>3</value></coordinates><team>8302</team><player1>108568</player1><stats><crosses>1</crosses></stats><id>8309314</id><n>239</n></value><value><event_incident_typefk>7</event_incident_typefk><elapsed>40</elapsed><sortorder>2</sortorder><type>cross</type><subtype>cross</subtype><coordinates><value>4</value><value>4</value></coordinates><team>8302</team><player1>209950</player1><stats><crosses>1</crosses></stats><id>8309328</id><n>255</n></value><value><event_incident_typefk>7</event_incident_typefk><elapsed>45</elapsed><elapsed_plus>1</elapsed_plus><sortorder>5</sortorder><type>cross</type><subtype>cross</subtype><coordinates><value>42</value><value>5</value></coordinates><team>8302</team><player1>33991</player1><stats><crosses>1</crosses></stats><id>8309361</id><n>286</n></value><value><event_incident_typefk>7</event_incident_typefk><elapsed>45</elapsed><elapsed_plus>2</elapsed_plus><sortorder>9</sortorder><type>cross</type><subtype>cross</subtype><coordinates><value>43</value><value>10</value></coordinates><team>8302</team><player1>33991</player1><stats><crosses>1</crosses></stats><id>8309365</id><n>298</n></value><value><event_incident_typefk>770</event_incident_typefk><elapsed>46</elapsed><sortorder>1</sortorder><type>cross</type><subtype>cross</subtype><coordinates><value>40</value><value>4</value></coordinates><team>8302</team><player1>33991</player1><stats><crosses>1</crosses></stats><id>8309400</id><n>311</n></value><value><event_incident_typefk>7</event_incident_typefk><elapsed>48</elapsed><sortorder>1</sortorder><type>cross</type><subtype>cross</subtype><coordinates><value>41</value><value>2</value></coordinates><team>8302</team><player1>33991</player1><stats><crosses>1</crosses></stats><id>8309409</id><n>319</n></value><value><event_incident_typefk>7</event_incident_typefk><elapsed>57</elapsed><sortorder>0</sortorder><type>cross</type><subtype>cross</subtype><coordinates><value>6</value><value>13</value></coordinates><team>8302</team><player1>209950</player1><stats><crosses>1</crosses></stats><id>8309475</id><n>386</n></value><value><event_incident_typefk>7</event_incident_typefk><elapsed>59</elapsed><sortorder>0</sortorder><type>cross</type><subtype>cross</subtype><coordinates><value>41</value><value>6</value></coordinates><team>8302</team><player1>33991</player1><stats><crosses>1</crosses></stats><id>8309489</id><n>401</n></value><value><event_incident_typefk>7</event_incident_typefk><elapsed>60</elapsed><sortorder>1</sortorder><type>cross</type><subtype>cross</subtype><coordinates><value>42</value><value>63</value></coordinates><team>10205</team><player1>629594</player1><stats><crosses>1</crosses></stats><id>8309498</id><n>411</n></value><value><event_incident_typefk>7</event_incident_typefk><elapsed>64</elapsed><sortorder>4</sortorder><type>cross</type><subtype>cross</subtype><coordinates><value>41</value><value>6</value></coordinates><team>8302</team><player1>33991</player1><stats><crosses>1</crosses></stats><id>8309521</id><n>424</n></value><value><event_incident_typefk>7</event_incident_typefk><elapsed>66</elapsed><sortorder>0</sortorder><type>cross</type><subtype>cross</subtype><coordinates><value>41</value><value>5</value></coordinates><team>8302</team><player1>189192</player1><stats><crosses>1</crosses></stats><id>8309528</id><n>431</n></value><value><event_incident_typefk>7</event_incident_typefk><elapsed>69</elapsed><sortorder>1</sortorder><type>cross</type><subtype>cross</subtype><coordinates><value>42</value><value>66</value></coordinates><team>10205</team><player1>629594</player1><stats><crosses>1</crosses></stats><id>8309549</id><n>449</n></value><value><event_incident_typefk>770</event_incident_typefk><elapsed>69</elapsed><sortorder>3</sortorder><type>cross</type><subtype>cross</subtype><coordinates><value>41</value><value>64</value></coordinates><team>10205</team><player1>629594</player1><stats><crosses>1</crosses></stats><id>8309552</id><n>452</n></value><value><event_incident_typefk>939</event_incident_typefk><elapsed>74</elapsed><sortorder>3</sortorder><type>cross</type><subtype>cross</subtype><coordinates><value>40</value><value>2</value></coordinates><team>8302</team><player1>33991</player1><stats><crosses>1</crosses></stats><id>8309589</id><n>479</n></value><value><event_incident_typefk>770</event_incident_typefk><elapsed>77</elapsed><sortorder>2</sortorder><type>cross</type><subtype>cross</subtype><coordinates><value>43</value><value>59</value></coordinates><team>10205</team><player1>629594</player1><stats><crosses>1</crosses></stats><id>8309599</id><n>484</n></value><value><event_incident_typefk>7</event_incident_typefk><elapsed>90</elapsed><elapsed_plus>1</elapsed_plus><sortorder>7</sortorder><type>cross</type><subtype>cross</subtype><coordinates><value>5</value><value>2</value></coordinates><team>8302</team><player1>210184</player1><stats><crosses>1</crosses></stats><id>8309798</id><n>548</n></value></cross><corner><value><event_incident_typefk>869</event_incident_typefk><elapsed>5</elapsed><sortorder>0</sortorder><type>corner</type><subtype>cross_right</subtype><coordinates><value>1</value><value>69</value></coordinates><team>10205</team><player1>37436</player1><stats><corners>1</corners><crosses>1</crosses></stats><id>8308819</id><n>32</n></value><value><event_incident_typefk>869</event_incident_typefk><elapsed>7</elapsed><sortorder>1</sortorder><type>corner</type><subtype>cross_right</subtype><coordinates><value>45</value><value>1</value></coordinates><team>8302</team><player1>108568</player1><stats><corners>1</corners><crosses>1</crosses></stats><id>8308884</id><n>49</n></value><value><event_incident_typefk>871</event_incident_typefk><elapsed>8</elapsed><sortorder>0</sortorder><type>corner</type><subtype>short_left</subtype><coordinates><value>1</value><value>1</value></coordinates><team>8302</team><player1>108568</player1><stats><corners>1</corners></stats><id>8308900</id><n>59</n></value><value><event_incident_typefk>869</event_incident_typefk><elapsed>17</elapsed><sortorder>0</sortorder><type>corner</type><subtype>cross_right</subtype><coordinates><value>45</value><value>1</value></coordinates><team>8302</team><player1>108568</player1><stats><corners>1</corners><crosses>1</crosses></stats><id>8309035</id><n>110</n></value><value><event_incident_typefk>873</event_incident_typefk><elapsed>24</elapsed><sortorder>0</sortorder><type>corner</type><subtype>short_right</subtype><coordinates><value>45</value><value>1</value></coordinates><team>8302</team><player1>108568</player1><stats><corners>1</corners></stats><id>8309153</id><n>155</n></value><value><event_incident_typefk>873</event_incident_typefk><elapsed>27</elapsed><sortorder>1</sortorder><type>corner</type><subtype>short_right</subtype><coordinates><value>1</value><value>69</value></coordinates><team>10205</team><player1>268282</player1><stats><corners>1</corners></stats><id>8309197</id><n>184</n></value><value><event_incident_typefk>867</event_incident_typefk><elapsed>41</elapsed><sortorder>2</sortorder><type>corner</type><subtype>cross_left</subtype><coordinates><value>45</value><value>69</value></coordinates><team>10205</team><player1>268282</player1><stats><corners>1</corners><crosses>1</crosses></stats><id>8309340</id><n>262</n></value><value><event_incident_typefk>867</event_incident_typefk><elapsed>53</elapsed><sortorder>1</sortorder><type>corner</type><subtype>cross_left</subtype><coordinates><value>45</value><value>69</value></coordinates><team>10205</team><player1>37436</player1><stats><corners>1</corners><crosses>1</crosses></stats><id>8309452</id><n>355</n></value><value><event_incident_typefk>869</event_incident_typefk><elapsed>69</elapsed><sortorder>0</sortorder><type>corner</type><subtype>cross_right</subtype><coordinates><value>1</value><value>69</value></coordinates><team>10205</team><player1>37436</player1><stats><corners>1</corners><crosses>1</crosses></stats><id>8309546</id><n>444</n></value></corner><possession><value><event_incident_typefk>1084</event_incident_typefk><elapsed>2</elapsed><sortorder>1</sortorder><type>None</type><subtype>possession</subtype><coordinates><value>7</value><value>52</value></coordinates><team>8302</team><id>8308755</id><n>15</n></value><value><event_incident_typefk>1084</event_incident_typefk><elapsed>4</elapsed><sortorder>0</sortorder><type>None</type><subtype>possession</subtype><coordinates><value>30</value><value>16</value></coordinates><team>10205</team><id>8308785</id><n>20</n></value><value><event_incident_typefk>1100</event_incident_typefk><elapsed>5</elapsed><comment>45</comment><sortorder>4</sortorder><type>special</type><subtype>possession</subtype><homepos>45</homepos><awaypos>55</awaypos><stats><homepos>45</homepos><awaypos>55</awaypos></stats><id>8308855</id><n>44</n></value><value><event_incident_typefk>1100</event_incident_typefk><elapsed>10</elapsed><comment>60</comment><sortorder>0</sortorder><type>special</type><subtype>possession</subtype><homepos>60</homepos><awaypos>40</awaypos><stats><homepos>60</homepos><awaypos>40</awaypos></stats><id>8308945</id><n>63</n></value><value><event_incident_typefk>1100</event_incident_typefk><elapsed>15</elapsed><comment>55</comment><sortorder>0</sortorder><type>special</type><subtype>possession</subtype><homepos>55</homepos><awaypos>45</awaypos><stats><homepos>55</homepos><awaypos>45</awaypos></stats><id>8309015</id><n>97</n></value><value><event_incident_typefk>1100</event_incident_typefk><elapsed>20</elapsed><comment>60</comment><sortorder>2</sortorder><type>special</type><subtype>possession</subtype><homepos>60</homepos><awaypos>40</awaypos><stats><homepos>60</homepos><awaypos>40</awaypos></stats><id>8309093</id><n>141</n></value><value><event_incident_typefk>1100</event_incident_typefk><elapsed>25</elapsed><comment>65</comment><sortorder>6</sortorder><type>special</type><subtype>possession</subtype><homepos>65</homepos><awaypos>35</awaypos><stats><homepos>65</homepos><awaypos>35</awaypos></stats><id>8309182</id><n>181</n></value><value><event_incident_typefk>1084</event_incident_typefk><elapsed>35</elapsed><sortorder>0</sortorder><type>None</type><subtype>possession</subtype><coordinates><value>16</value><value>25</value></coordinates><team>10205</team><id>8309280</id><n>207</n></value><value><event_incident_typefk>1100</event_incident_typefk><elapsed>35</elapsed><comment>51</comment><sortorder>1</sortorder><type>special</type><subtype>possession</subtype><homepos>51</homepos><awaypos>49</awaypos><stats><homepos>51</homepos><awaypos>49</awaypos></stats><id>8309282</id><n>209</n></value><value><event_incident_typefk>1100</event_incident_typefk><elapsed>40</elapsed><comment>52</comment><sortorder>1</sortorder><type>special</type><subtype>possession</subtype><homepos>52</homepos><awaypos>48</awaypos><stats><homepos>52</homepos><awaypos>48</awaypos></stats><id>8309327</id><n>253</n></value><value><event_incident_typefk>1100</event_incident_typefk><elapsed>45</elapsed><comment>49</comment><sortorder>1</sortorder><type>special</type><subtype>possession</subtype><homepos>49</homepos><awaypos>51</awaypos><stats><homepos>49</homepos><awaypos>51</awaypos></stats><id>8309357</id><n>275</n></value><value><event_incident_typefk>1100</event_incident_typefk><elapsed>45</elapsed><elapsed_plus>3</elapsed_plus><comment>50</comment><sortorder>12</sortorder><type>special</type><subtype>possession</subtype><homepos>50</homepos><awaypos>50</awaypos><stats><homepos>50</homepos><awaypos>50</awaypos></stats><id>8309368</id><n>303</n></value><value><event_incident_typefk>1100</event_incident_typefk><elapsed>50</elapsed><comment>49</comment><sortorder>0</sortorder><type>special</type><subtype>possession</subtype><homepos>49</homepos><awaypos>51</awaypos><stats><homepos>49</homepos><awaypos>51</awaypos></stats><id>8309424</id><n>335</n></value><value><event_incident_typefk>1100</event_incident_typefk><elapsed>55</elapsed><comment>48</comment><sortorder>1</sortorder><type>special</type><subtype>possession</subtype><homepos>48</homepos><awaypos>52</awaypos><stats><homepos>48</homepos><awaypos>52</awaypos></stats><id>8309464</id><n>372</n></value><value><event_incident_typefk>1100</event_incident_typefk><elapsed>65</elapsed><comment>51</comment><sortorder>1</sortorder><type>special</type><subtype>possession</subtype><homepos>51</homepos><awaypos>49</awaypos><stats><homepos>51</homepos><awaypos>49</awaypos></stats><id>8309527</id><n>429</n></value><value><event_incident_typefk>1100</event_incident_typefk><elapsed>70</elapsed><comment>51</comment><sortorder>0</sortorder><type>special</type><subtype>possession</subtype><homepos>51</homepos><awaypos>49</awaypos><stats><homepos>51</homepos><awaypos>49</awaypos></stats><id>8309559</id><n>455</n></value><value><event_incident_typefk>1100</event_incident_typefk><elapsed>75</elapsed><comment>53</comment><sortorder>0</sortorder><type>special</type><subtype>possession</subtype><homepos>53</homepos><awaypos>47</awaypos><stats><homepos>53</homepos><awaypos>47</awaypos></stats><id>8309591</id><n>480</n></value><value><event_incident_typefk>1100</event_incident_typefk><elapsed>80</elapsed><comment>50</comment><sortorder>2</sortorder><type>special</type><subtype>possession</subtype><homepos>50</homepos><awaypos>50</awaypos><stats><homepos>50</homepos><awaypos>50</awaypos></stats><id>8309613</id><n>492</n></value><value><event_incident_typefk>1100</event_incident_typefk><elapsed>85</elapsed><comment>49</comment><sortorder>0</sortorder><type>special</type><subtype>possession</subtype><homepos>49</homepos><awaypos>51</awaypos><stats><homepos>49</homepos><awaypos>51</awaypos></stats><id>8309636</id><n>506</n></value><value><event_incident_typefk>1084</event_incident_typefk><elapsed>87</elapsed><sortorder>2</sortorder><type>None</type><subtype>possession</subtype><coordinates><value>14</value><value>48</value></coordinates><team>8302</team><id>8309650</id><n>518</n></value><value><event_incident_typefk>1100</event_incident_typefk><elapsed>90</elapsed><comment>50</comment><sortorder>2</sortorder><type>special</type><subtype>possession</subtype><homepos>50</homepos><awaypos>50</awaypos><stats><homepos>50</homepos><awaypos>50</awaypos></stats><id>8309792</id><n>536</n></value><value><event_incident_typefk>1084</event_incident_typefk><elapsed>90</elapsed><elapsed_plus>4</elapsed_plus><sortorder>17</sortorder><type>None</type><subtype>possession</subtype><coordinates><value>38</value><value>25</value></coordinates><team>10205</team><id>8309810</id><n>577</n></value><value><event_incident_typefk>1100</event_incident_typefk><elapsed>90</elapsed><elapsed_plus>5</elapsed_plus><comment>49</comment><sortorder>21</sortorder><type>special</type><subtype>possession</subtype><homepos>49</homepos><awaypos>51</awaypos><stats><homepos>49</homepos><awaypos>51</awaypos></stats><id>8309814</id><n>583</n></value><value><event_incident_typefk>1100</event_incident_typefk><elapsed>90</elapsed><elapsed_plus>6</elapsed_plus><comment>49</comment><sortorder>23</sortorder><type>special</type><subtype>possession</subtype><homepos>49</homepos><awaypos>51</awaypos><stats><homepos>49</homepos><awaypos>51</awaypos></stats><id>8309816</id><n>587</n></value></possession></item>